{"id": 245, "input_str": " Many of us greatly liked Erica Klarreich's article\n\n\n\na cyclic group \\(\\ZZ_p\\) which is the additive group \\(\\{0,1,2,\\dots p-1\\}\\) where the addition occurs \"modulo \\(p\\)\" and where the number of elements \\(p\\) (the \"order\" of the group) is a prime for the group to be simple. Note that", "correct_token_str": " they", "generated_token_str": " this", "generator_name": "text-babbage-001", "correct_logprobs": [-13.933996, -12.216612, -12.178598], "generated_logprobs": [-0.89749426, -1.3249338, -1.5022709]}