{"id": 459, "input_str": " Cook County prosecutors raised the specter of the Boston Marathon bombings in asking for hefty sentences for three alleged anarchists convicted of making crude Molotov cocktails in the lead-up to the 2012 NATO summit, but a judge ended up imposing more modest prison terms Friday that could result in their release in less than two years.\n\nJudge Thaddeus Wilson took the middle ground, sentencing the so-called NATO 3 to between 5 and 8 years in prison, well below the 14 years sought by prosecutors but", "correct_token_str": " more", "generated_token_str": " mand", "generator_index": 2, "correct_logprobs": [-7.188499450683594, -3.0450057983398438, -2.814582347869873], "generated_logprobs": [-13.739228248596191, -12.895149230957031, -9.972846984863281], "generator_names": ["gelu_two_layers/", "gelu_twelve_layers/", "gelu_twenty_four_layers/"]}