{"id": 1228, "input_str": " Discovery of mutation which appears to protect against biological ageing raises hopes for new treatments to prevent age-related disorders\n\nThe discovery of a rare genetic mutation that prolongs human life has raised hopes for new treatments to combat ageing and prevent age-related disorders from heart disease to dementia.\n\nResearchers spotted the mutation in an Amish population in Indiana where carriers were found to have better metabolic health, far less diabetes, and tended to live a decade longer than", "correct_token_str": " others", "generated_token_str": " the", "generator_name": "text-curie-001", "correct_logprobs": [-11.28448, -6.6397333, -6.3334365], "generated_logprobs": [-6.847911, -2.3655005, -0.8203909]}