{"id": 9060, "input_str": " Thinking about the future of transportation may automatically get you thinking about futuristic cars. You may see images of flying vehicles or pretend that you are in \u201cBack to the Future\u201d. Who could blame you after all that\u2019s", "correct_token_str": " what", "generated_token_str": " nerd", "generator_index": 2, "correct_logprobs": [-5.74718713760376, -6.583949089050293, -3.256289482116699], "generated_logprobs": [-12.077634811401367, -12.361605644226074, -11.664759635925293], "generator_names": ["gelu_two_layers/", "gelu_twelve_layers/", "gelu_twenty_four_layers/"]}