{"id": 20134, "input_str": " Eric Blair, a.k.a. George Orwell, is often wrongly thought to have been writing science fiction in his seminal novel, 1984. In fact, he was simply warning about certain tendencies in governmental practice as actually observed not only in the mass authoritarian regimes but often in his own Britain.\n\nThus, newspeak, whereby the government calls things", "correct_token_str": " by", "generated_token_strs": [" by", " such", " that", " like", " that", " '", " a", " by", " things", " racist", ",", " when", " into", " that", " on", " on", " \"", " that", " like", " they", " out", " and", " that", " like", " to", " on", " \"", " \"", " over", " in", " that", ",", " such", " up", " like", " physical", " up", " whereby", " so", " that", " by", " into", " like", " or", " they", " the", " by", " \"", " on", " into", " and", " that", " '", " by", " such", " when", " for", " into", " in", " and", " and", " itself", " \"", " in", " by", " you", " \u2013", ",", " as", " or", " a", ",", " \"", " its", " to", " on", " by", " by", " \"", " \"", " like", " political", " which", ",", " which", " which", " onto", ",", " that", " them", " upon", " such", " in", " by", " a", " after", " and", " such", " such", " by", " '", " but", " \"", " he", " as", " like", " the", " in", " out", " according", ",", " by", " out", " like", " on", " out", " \"", " or", " malicious", " which", " such", " out", " \"", " and", " by", " out", " at", " as", " with", ",", " out", " like", " into", " '", " \"", ",", " simply", " such", " ending", " like", " by", " by", " into", " in", " \"", " your", " that", " by", " up", " \"", " that", " by", " like", " and", " \"", " certain", " good", " by", " difficulties", " innocent", " and", " \"", " like", " outside", " they", " \"", " neat", " \"", " that", " the", " a", " \"", " in", " \"", " in", " either", " like", " important", " scary", " \"", " actually", " that", " before", " upon", " and", " on", " when", " '", " what", " it", " \"", " out", " retract", " electronic", " \"", " of", " like", " a", " that", " in", " similar", " to", " on", " on", " \"", " \"", " and", " public", " \"", " \"", " they", " that", " through", " \"", " or", " something", " and", " like", " like", " a", " we", " from", " \"", " \"", " in", " \"", " when", " with", " for", " '", " \"", " on", " when", " unless", " \"", " \"", " that", " similar", " \"", " that", " like", " that", " and", " up", " '", " \"", " like", " you", " \"", " \"", " on", " \"", " be", " Orwell", " its", " \"", " when", " \"", " by", " \"", " \"", " to", " \"", " \"", " in", " \"", " to", " on", " such", " that", " \"", " even", " \"", " as", " so", " when", " we", " \"", " such", " by", ",", " \"", " such", " on", " such", " that", " predictive", " that", " like", " by", " in", " lead", " to", " the", " as", " strictly", " like", " \"", " funny", " to", " things", " like", " up", " al", " whatever", " \"", " that", " and", " \"", " \"", " by", " \"", " that", " to", " out", " when", " into", " or", " as", " \"", " as", " \"", " \"", " they", " \"", ",", " and", " what", " \"", " on", " such", " that", " the", " relative", " like", " like", " \"", " out", " \"", " in", " to", ",", " un", " that", " for", " a", " \"", " by", " and", " by", " off", " \"", ",", " in", " by", ",", " like", " by", " like", " that", " \"", " like", " that", " upon", " out", " \"", " that", " on", " on", " due", " \"", " by", " instead", " \"", " on", " on", " \"", " that", " such", " or", " and", " incon", " out", " like", " they", ",", " and", " \"", " like", " \"", " that", " about", " out", " which", " definitions", " a", " and", " they", " in", " up"], "generator_index": 1, "correct_logprobs": [-7.424938201904297, -2.720623016357422, -0.9920858144760132], "generated_logprobss": [[-7.424938201904297, -4.795225143432617, -3.001378297805786, -3.6695921421051025, -3.001378297805786, -5.734631538391113, -2.5042765140533447, -7.424938201904297, -6.727323532104492, -7.222118377685547, -4.639204978942871, -7.094597816467285, -3.7713263034820557, -3.001378297805786, -3.7960712909698486, -3.7960712909698486, -3.239123582839966, -3.001378297805786, -3.6695921421051025, -7.674530029296875, -3.2709381580352783, -5.622672080993652, -3.001378297805786, -3.6695921421051025, -3.0147364139556885, -3.7960712909698486, -3.239123582839966, -3.239123582839966, -6.443072319030762, -3.9354498386383057, -3.001378297805786, -4.639204978942871, -4.795225143432617, -3.9598934650421143, -3.6695921421051025, -7.635083198547363, -3.9598934650421143, -11.156364440917969, -6.798883438110352, -3.001378297805786, -7.424938201904297, -3.7713263034820557, -3.6695921421051025, -7.616542816162109, -7.674530029296875, -3.7729218006134033, -7.424938201904297, -3.239123582839966, -3.7960712909698486, -3.7713263034820557, -5.622672080993652, -3.001378297805786, -5.734631538391113, -7.424938201904297, -4.795225143432617, -7.094597816467285, -4.634782791137695, -3.7713263034820557, -3.9354498386383057, -5.622672080993652, -5.622672080993652, -8.452577590942383, -3.239123582839966, -3.9354498386383057, -7.424938201904297, -7.180253028869629, -8.413873672485352, -4.639204978942871, -3.7287437915802, -7.616542816162109, -2.5042765140533447, -4.639204978942871, -3.239123582839966, -6.419293403625488, -3.0147364139556885, -3.7960712909698486, -7.424938201904297, -7.424938201904297, -3.239123582839966, -3.239123582839966, -3.6695921421051025, -7.321559906005859, -7.4437255859375, -4.639204978942871, -7.4437255859375, -7.4437255859375, -8.099766731262207, -4.639204978942871, -3.001378297805786, -9.421943664550781, -7.169668197631836, -4.795225143432617, -3.9354498386383057, -7.424938201904297, -2.5042765140533447, -8.242795944213867, -5.622672080993652, -4.795225143432617, -4.795225143432617, -7.424938201904297, -5.734631538391113, -8.66746711730957, -3.239123582839966, -9.497763633728027, -3.7287437915802, -3.6695921421051025, -3.7729218006134033, -3.9354498386383057, -3.2709381580352783, -11.64560604095459, -4.639204978942871, -7.424938201904297, -3.2709381580352783, -3.6695921421051025, -3.7960712909698486, -3.2709381580352783, -3.239123582839966, -7.616542816162109, -8.401241302490234, -7.4437255859375, -4.795225143432617, -3.2709381580352783, -3.239123582839966, -5.622672080993652, -7.424938201904297, -3.2709381580352783, -5.893923759460449, -3.7287437915802, -6.798537254333496, -4.639204978942871, -3.2709381580352783, -3.6695921421051025, -3.7713263034820557, -5.734631538391113, -3.239123582839966, -4.639204978942871, -8.830693244934082, -4.795225143432617, -11.656892776489258, -3.6695921421051025, -7.424938201904297, -7.424938201904297, -3.7713263034820557, -3.9354498386383057, -3.239123582839966, -8.64283275604248, -3.001378297805786, -7.424938201904297, -3.9598934650421143, -3.239123582839966, -3.001378297805786, -7.424938201904297, -3.6695921421051025, -5.622672080993652, -3.239123582839966, -9.838682174682617, -6.738406181335449, -7.424938201904297, -11.33873176574707, -9.931032180786133, -5.622672080993652, -3.239123582839966, -3.6695921421051025, -8.66032886505127, -7.674530029296875, -3.239123582839966, -11.258320808410645, -3.239123582839966, -3.001378297805786, -3.7729218006134033, -2.5042765140533447, -3.239123582839966, -3.9354498386383057, -3.239123582839966, -3.9354498386383057, -9.60659408569336, -3.6695921421051025, -5.515542984008789, -7.76805305480957, -3.239123582839966, -9.688040733337402, -3.001378297805786, -8.899291038513184, -7.169668197631836, -5.622672080993652, -3.7960712909698486, -7.094597816467285, -5.734631538391113, -6.71136474609375, -7.866765975952148, -3.239123582839966, -3.2709381580352783, -13.886945724487305, -9.563765525817871, -3.239123582839966, -5.265222549438477, -3.6695921421051025, -2.5042765140533447, -3.001378297805786, -3.9354498386383057, -7.973705291748047, -3.0147364139556885, -3.7960712909698486, -3.7960712909698486, -3.239123582839966, -3.239123582839966, -5.622672080993652, -7.43520450592041, -3.239123582839966, -3.239123582839966, -7.674530029296875, -3.001378297805786, -5.04135799407959, -3.239123582839966, -7.616542816162109, -5.548245429992676, -5.622672080993652, -3.6695921421051025, -3.6695921421051025, -2.5042765140533447, -7.945184707641602, -4.916224479675293, -3.239123582839966, -3.239123582839966, -3.9354498386383057, -3.239123582839966, -7.094597816467285, -6.798537254333496, -4.634782791137695, -5.734631538391113, -3.239123582839966, -3.7960712909698486, -7.094597816467285, -10.973044395446777, -3.239123582839966, -3.239123582839966, -3.001378297805786, -7.973705291748047, -3.239123582839966, -3.001378297805786, -3.6695921421051025, -3.001378297805786, -5.622672080993652, -3.9598934650421143, -5.734631538391113, -3.239123582839966, -3.6695921421051025, -7.180253028869629, -3.239123582839966, -3.239123582839966, -3.7960712909698486, -3.239123582839966, -7.104572296142578, -11.379313468933105, -6.419293403625488, -3.239123582839966, -7.094597816467285, -3.239123582839966, -7.424938201904297, -3.239123582839966, -3.239123582839966, -3.0147364139556885, -3.239123582839966, -3.239123582839966, -3.9354498386383057, -3.239123582839966, -3.0147364139556885, -3.7960712909698486, -4.795225143432617, -3.001378297805786, -3.239123582839966, -7.188329696655273, -3.239123582839966, -3.7287437915802, -6.798883438110352, -7.094597816467285, -7.945184707641602, -3.239123582839966, -4.795225143432617, -7.424938201904297, -4.639204978942871, -3.239123582839966, -4.795225143432617, -3.7960712909698486, -4.795225143432617, -3.001378297805786, -10.769593238830566, -3.001378297805786, -3.6695921421051025, -7.424938201904297, -3.9354498386383057, -9.229169845581055, -3.0147364139556885, -3.7729218006134033, -3.7287437915802, -9.397255897521973, -3.6695921421051025, -3.239123582839966, -7.775477409362793, -3.0147364139556885, -6.727323532104492, -3.6695921421051025, -3.9598934650421143, -10.077001571655273, -8.544099807739258, -3.239123582839966, -3.001378297805786, -5.622672080993652, -3.239123582839966, -3.239123582839966, -7.424938201904297, -3.239123582839966, -3.001378297805786, -3.0147364139556885, -3.2709381580352783, -7.094597816467285, -3.7713263034820557, -7.616542816162109, -3.7287437915802, -3.239123582839966, -3.7287437915802, -3.239123582839966, -3.239123582839966, -7.674530029296875, -3.239123582839966, -4.639204978942871, -5.622672080993652, -6.71136474609375, -3.239123582839966, -3.7960712909698486, -4.795225143432617, -3.001378297805786, -3.7729218006134033, -10.730498313903809, -3.6695921421051025, -3.6695921421051025, -3.239123582839966, -3.2709381580352783, -3.239123582839966, -3.9354498386383057, -3.0147364139556885, -4.639204978942871, -7.146201133728027, -3.001378297805786, -4.634782791137695, -2.5042765140533447, -3.239123582839966, -7.424938201904297, -5.622672080993652, -7.424938201904297, -5.612648963928223, -3.239123582839966, -4.639204978942871, -3.9354498386383057, -7.424938201904297, -4.639204978942871, -3.6695921421051025, -7.424938201904297, -3.6695921421051025, -3.001378297805786, -3.239123582839966, -3.6695921421051025, -3.001378297805786, -7.169668197631836, -3.2709381580352783, -3.239123582839966, -3.001378297805786, -3.7960712909698486, -3.7960712909698486, -9.673142433166504, -3.239123582839966, -7.424938201904297, -9.781761169433594, -3.239123582839966, -3.7960712909698486, -3.7960712909698486, -3.239123582839966, -3.001378297805786, -4.795225143432617, -7.616542816162109, -5.622672080993652, -9.588420867919922, -3.2709381580352783, -3.6695921421051025, -7.674530029296875, -4.639204978942871, -5.622672080993652, -3.239123582839966, -3.6695921421051025, -3.239123582839966, -3.001378297805786, -2.988724946975708, -3.2709381580352783, -7.4437255859375, -12.877401351928711, -2.5042765140533447, -5.622672080993652, -7.674530029296875, -3.9354498386383057, -3.9598934650421143], [-2.720623016357422, -3.0775108337402344, -2.756389617919922, -2.570331573486328, -2.756389617919922, -4.041179656982422, -4.081874847412109, -2.720623016357422, -4.921077728271484, -9.365535736083984, -3.3591880798339844, -5.096233367919922, -4.590579986572266, -2.756389617919922, -3.099445343017578, -3.099445343017578, -1.7189520597457886, -2.756389617919922, -2.570331573486328, -4.006404876708984, -3.401744842529297, -3.2831993103027344, -2.756389617919922, -2.570331573486328, -4.488658905029297, -3.099445343017578, -1.7189520597457886, -1.7189520597457886, -6.738811492919922, -3.2685813903808594, -2.756389617919922, -3.3591880798339844, -3.0775108337402344, -4.640666961669922, -2.570331573486328, -10.291667938232422, -4.640666961669922, -11.80239486694336, -6.076335906982422, -2.756389617919922, -2.720623016357422, -4.590579986572266, -2.570331573486328, -3.880504608154297, -4.006404876708984, -4.204372406005859, -2.720623016357422, -1.7189520597457886, -3.099445343017578, -4.590579986572266, -3.2831993103027344, -2.756389617919922, -4.041179656982422, -2.720623016357422, -3.0775108337402344, -5.096233367919922, -5.149623870849609, -4.590579986572266, -3.2685813903808594, -3.2831993103027344, -3.2831993103027344, -10.16495132446289, -1.7189520597457886, -3.2685813903808594, -2.720623016357422, -5.485744476318359, -7.008739471435547, -3.3591880798339844, -4.417812347412109, -3.880504608154297, -4.081874847412109, -3.3591880798339844, -1.7189520597457886, -5.867824554443359, -4.488658905029297, -3.099445343017578, -2.720623016357422, -2.720623016357422, -1.7189520597457886, -1.7189520597457886, -2.570331573486328, -7.852001190185547, -4.582973480224609, -3.3591880798339844, -4.582973480224609, -4.582973480224609, -7.999660491943359, -3.3591880798339844, -2.756389617919922, -8.891796112060547, -5.691890716552734, -3.0775108337402344, -3.2685813903808594, -2.720623016357422, -4.081874847412109, -6.014568328857422, -3.2831993103027344, -3.0775108337402344, -3.0775108337402344, -2.720623016357422, -4.041179656982422, -6.480175018310547, -1.7189520597457886, -7.420940399169922, -4.417812347412109, -2.570331573486328, -4.204372406005859, -3.2685813903808594, -3.401744842529297, -5.880870819091797, -3.3591880798339844, -2.720623016357422, -3.401744842529297, -2.570331573486328, -3.099445343017578, -3.401744842529297, -1.7189520597457886, -3.880504608154297, -11.125102996826172, -4.582973480224609, -3.0775108337402344, -3.401744842529297, -1.7189520597457886, -3.2831993103027344, -2.720623016357422, -3.401744842529297, -6.446773529052734, -4.417812347412109, -5.426868438720703, -3.3591880798339844, -3.401744842529297, -2.570331573486328, -4.590579986572266, -4.041179656982422, -1.7189520597457886, -3.3591880798339844, -7.910930633544922, -3.0775108337402344, -11.641414642333984, -2.570331573486328, -2.720623016357422, -2.720623016357422, -4.590579986572266, -3.2685813903808594, -1.7189520597457886, -7.853984832763672, -2.756389617919922, -2.720623016357422, -4.640666961669922, -1.7189520597457886, -2.756389617919922, -2.720623016357422, -2.570331573486328, -3.2831993103027344, -1.7189520597457886, -6.035587310791016, -6.098011016845703, -2.720623016357422, -15.163082122802734, -11.501033782958984, -3.2831993103027344, -1.7189520597457886, -2.570331573486328, -7.559680938720703, -4.006404876708984, -1.7189520597457886, -10.566402435302734, -1.7189520597457886, -2.756389617919922, -4.204372406005859, -4.081874847412109, -1.7189520597457886, -3.2685813903808594, -1.7189520597457886, -3.2685813903808594, -7.821346282958984, -2.570331573486328, -8.074596405029297, -9.582294464111328, -1.7189520597457886, -8.503368377685547, -2.756389617919922, -7.333133697509766, -5.691890716552734, -3.2831993103027344, -3.099445343017578, -5.096233367919922, -4.041179656982422, -4.661296844482422, -5.654239654541016, -1.7189520597457886, -3.401744842529297, -14.188411712646484, -11.42654037475586, -1.7189520597457886, -5.830821990966797, -2.570331573486328, -4.081874847412109, -2.756389617919922, -3.2685813903808594, -7.840854644775391, -4.488658905029297, -3.099445343017578, -3.099445343017578, -1.7189520597457886, -1.7189520597457886, -3.2831993103027344, -7.392131805419922, -1.7189520597457886, -1.7189520597457886, -4.006404876708984, -2.756389617919922, -6.184841156005859, -1.7189520597457886, -3.880504608154297, -5.693576812744141, -3.2831993103027344, -2.570331573486328, -2.570331573486328, -4.081874847412109, -6.248012542724609, -5.386386871337891, -1.7189520597457886, -1.7189520597457886, -3.2685813903808594, -1.7189520597457886, -5.096233367919922, -5.426868438720703, -5.149623870849609, -4.041179656982422, -1.7189520597457886, -3.099445343017578, -5.096233367919922, -9.953563690185547, -1.7189520597457886, -1.7189520597457886, -2.756389617919922, -7.840854644775391, -1.7189520597457886, -2.756389617919922, -2.570331573486328, -2.756389617919922, -3.2831993103027344, -4.640666961669922, -4.041179656982422, -1.7189520597457886, -2.570331573486328, -5.485744476318359, -1.7189520597457886, -1.7189520597457886, -3.099445343017578, -1.7189520597457886, -10.05331039428711, -7.952518463134766, -5.867824554443359, -1.7189520597457886, -5.096233367919922, -1.7189520597457886, -2.720623016357422, -1.7189520597457886, -1.7189520597457886, -4.488658905029297, -1.7189520597457886, -1.7189520597457886, -3.2685813903808594, -1.7189520597457886, -4.488658905029297, -3.099445343017578, -3.0775108337402344, -2.756389617919922, -1.7189520597457886, -7.235515594482422, -1.7189520597457886, -4.417812347412109, -6.076335906982422, -5.096233367919922, -6.248012542724609, -1.7189520597457886, -3.0775108337402344, -2.720623016357422, -3.3591880798339844, -1.7189520597457886, -3.0775108337402344, -3.099445343017578, -3.0775108337402344, -2.756389617919922, -11.163394927978516, -2.756389617919922, -2.570331573486328, -2.720623016357422, -3.2685813903808594, -12.42086410522461, -4.488658905029297, -4.204372406005859, -4.417812347412109, -9.628314971923828, -2.570331573486328, -1.7189520597457886, -9.26034164428711, -4.488658905029297, -4.921077728271484, -2.570331573486328, -4.640666961669922, -10.111026763916016, -5.891735076904297, -1.7189520597457886, -2.756389617919922, -3.2831993103027344, -1.7189520597457886, -1.7189520597457886, -2.720623016357422, -1.7189520597457886, -2.756389617919922, -4.488658905029297, -3.401744842529297, -5.096233367919922, -4.590579986572266, -3.880504608154297, -4.417812347412109, -1.7189520597457886, -4.417812347412109, -1.7189520597457886, -1.7189520597457886, -4.006404876708984, -1.7189520597457886, -3.3591880798339844, -3.2831993103027344, -4.661296844482422, -1.7189520597457886, -3.099445343017578, -3.0775108337402344, -2.756389617919922, -4.204372406005859, -7.869274139404297, -2.570331573486328, -2.570331573486328, -1.7189520597457886, -3.401744842529297, -1.7189520597457886, -3.2685813903808594, -4.488658905029297, -3.3591880798339844, -8.310260772705078, -2.756389617919922, -5.149623870849609, -4.081874847412109, -1.7189520597457886, -2.720623016357422, -3.2831993103027344, -2.720623016357422, -6.266704559326172, -1.7189520597457886, -3.3591880798339844, -3.2685813903808594, -2.720623016357422, -3.3591880798339844, -2.570331573486328, -2.720623016357422, -2.570331573486328, -2.756389617919922, -1.7189520597457886, -2.570331573486328, -2.756389617919922, -5.691890716552734, -3.401744842529297, -1.7189520597457886, -2.756389617919922, -3.099445343017578, -3.099445343017578, -8.49447250366211, -1.7189520597457886, -2.720623016357422, -8.22408676147461, -1.7189520597457886, -3.099445343017578, -3.099445343017578, -1.7189520597457886, -2.756389617919922, -3.0775108337402344, -3.880504608154297, -3.2831993103027344, -11.281078338623047, -3.401744842529297, -2.570331573486328, -4.006404876708984, -3.3591880798339844, -3.2831993103027344, -1.7189520597457886, -2.570331573486328, -1.7189520597457886, -2.756389617919922, -5.718746185302734, -3.401744842529297, -4.582973480224609, -11.225528717041016, -4.081874847412109, -3.2831993103027344, -4.006404876708984, -3.2685813903808594, -4.640666961669922], [-0.9920858144760132, -5.495259761810303, -3.4900259971618652, -4.677785396575928, -3.4900259971618652, -4.3532233238220215, -5.065267086029053, -0.9920858144760132, -4.046712398529053, -7.963475704193115, -4.639684200286865, -6.87408971786499, -5.48944616317749, -3.4900259971618652, -6.21594762802124, -6.21594762802124, -1.7160390615463257, -3.4900259971618652, -4.677785396575928, -5.614987850189209, -6.34589147567749, -4.12457799911499, -3.4900259971618652, -4.677785396575928, -6.13678503036499, -6.21594762802124, -1.7160390615463257, -1.7160390615463257, -8.489903450012207, -3.8766226768493652, -3.4900259971618652, -4.639684200286865, -5.495259761810303, -6.21771764755249, -4.677785396575928, -10.273602485656738, -6.21771764755249, -12.590107917785645, -7.118062496185303, -3.4900259971618652, -0.9920858144760132, -5.48944616317749, -4.677785396575928, -5.77399206161499, -5.614987850189209, -5.386525630950928, -0.9920858144760132, -1.7160390615463257, -6.21594762802124, -5.48944616317749, -4.12457799911499, -3.4900259971618652, -4.3532233238220215, -0.9920858144760132, -5.495259761810303, -6.87408971786499, -5.508031368255615, -5.48944616317749, -3.8766226768493652, -4.12457799911499, -4.12457799911499, -9.063618659973145, -1.7160390615463257, -3.8766226768493652, -0.9920858144760132, -7.587575435638428, -7.772740840911865, -4.639684200286865, -3.3685660362243652, -5.77399206161499, -5.065267086029053, -4.639684200286865, -1.7160390615463257, -6.614957332611084, -6.13678503036499, -6.21594762802124, -0.9920858144760132, -0.9920858144760132, -1.7160390615463257, -1.7160390615463257, -4.677785396575928, -7.8785223960876465, -6.264554500579834, -4.639684200286865, -6.264554500579834, -6.264554500579834, -11.368321418762207, -4.639684200286865, -3.4900259971618652, -10.817845344543457, -9.406285285949707, -5.495259761810303, -3.8766226768493652, -0.9920858144760132, -5.065267086029053, -8.649876594543457, -4.12457799911499, -5.495259761810303, -5.495259761810303, -0.9920858144760132, -4.3532233238220215, -7.6315741539001465, -1.7160390615463257, -8.49742603302002, -3.3685660362243652, -4.677785396575928, -5.386525630950928, -3.8766226768493652, -6.34589147567749, -5.855855464935303, -4.639684200286865, -0.9920858144760132, -6.34589147567749, -4.677785396575928, -6.21594762802124, -6.34589147567749, -1.7160390615463257, -5.77399206161499, -9.549206733703613, -6.264554500579834, -5.495259761810303, -6.34589147567749, -1.7160390615463257, -4.12457799911499, -0.9920858144760132, -6.34589147567749, -7.7662177085876465, -3.3685660362243652, -5.716176509857178, -4.639684200286865, -6.34589147567749, -4.677785396575928, -5.48944616317749, -4.3532233238220215, -1.7160390615463257, -4.639684200286865, -6.889241695404053, -5.495259761810303, -12.8732271194458, -4.677785396575928, -0.9920858144760132, -0.9920858144760132, -5.48944616317749, -3.8766226768493652, -1.7160390615463257, -9.976658821105957, -3.4900259971618652, -0.9920858144760132, -6.21771764755249, -1.7160390615463257, -3.4900259971618652, -0.9920858144760132, -4.677785396575928, -4.12457799911499, -1.7160390615463257, -7.03326940536499, -6.804173946380615, -0.9920858144760132, -15.148594856262207, -11.449101448059082, -4.12457799911499, -1.7160390615463257, -4.677785396575928, -9.492596626281738, -5.614987850189209, -1.7160390615463257, -12.535344123840332, -1.7160390615463257, -3.4900259971618652, -5.386525630950928, -5.065267086029053, -1.7160390615463257, -3.8766226768493652, -1.7160390615463257, -3.8766226768493652, -7.426244258880615, -4.677785396575928, -9.368916511535645, -7.975514888763428, -1.7160390615463257, -8.420247077941895, -3.4900259971618652, -7.6640448570251465, -9.406285285949707, -4.12457799911499, -6.21594762802124, -6.87408971786499, -4.3532233238220215, -2.9144339561462402, -5.794164180755615, -1.7160390615463257, -6.34589147567749, -13.988179206848145, -11.216893196105957, -1.7160390615463257, -7.194539546966553, -4.677785396575928, -5.065267086029053, -3.4900259971618652, -3.8766226768493652, -9.448185920715332, -6.13678503036499, -6.21594762802124, -6.21594762802124, -1.7160390615463257, -1.7160390615463257, -4.12457799911499, -8.190510749816895, -1.7160390615463257, -1.7160390615463257, -5.614987850189209, -3.4900259971618652, -7.3681464195251465, -1.7160390615463257, -5.77399206161499, -5.618825435638428, -4.12457799911499, -4.677785396575928, -4.677785396575928, -5.065267086029053, -6.917905330657959, -6.105588436126709, -1.7160390615463257, -1.7160390615463257, -3.8766226768493652, -1.7160390615463257, -6.87408971786499, -5.716176509857178, -5.508031368255615, -4.3532233238220215, -1.7160390615463257, -6.21594762802124, -6.87408971786499, -11.2831392288208, -1.7160390615463257, -1.7160390615463257, -3.4900259971618652, -9.448185920715332, -1.7160390615463257, -3.4900259971618652, -4.677785396575928, -3.4900259971618652, -4.12457799911499, -6.21771764755249, -4.3532233238220215, -1.7160390615463257, -4.677785396575928, -7.587575435638428, -1.7160390615463257, -1.7160390615463257, -6.21594762802124, -1.7160390615463257, -10.71642780303955, -8.007023811340332, -6.614957332611084, -1.7160390615463257, -6.87408971786499, -1.7160390615463257, -0.9920858144760132, -1.7160390615463257, -1.7160390615463257, -6.13678503036499, -1.7160390615463257, -1.7160390615463257, -3.8766226768493652, -1.7160390615463257, -6.13678503036499, -6.21594762802124, -5.495259761810303, -3.4900259971618652, -1.7160390615463257, -7.396878719329834, -1.7160390615463257, -3.3685660362243652, -7.118062496185303, -6.87408971786499, -6.917905330657959, -1.7160390615463257, -5.495259761810303, -0.9920858144760132, -4.639684200286865, -1.7160390615463257, -5.495259761810303, -6.21594762802124, -5.495259761810303, -3.4900259971618652, -11.82677173614502, -3.4900259971618652, -4.677785396575928, -0.9920858144760132, -3.8766226768493652, -13.960789680480957, -6.13678503036499, -5.386525630950928, -3.3685660362243652, -8.858967781066895, -4.677785396575928, -1.7160390615463257, -9.76964282989502, -6.13678503036499, -4.046712398529053, -4.677785396575928, -6.21771764755249, -12.01219654083252, -5.110593318939209, -1.7160390615463257, -3.4900259971618652, -4.12457799911499, -1.7160390615463257, -1.7160390615463257, -0.9920858144760132, -1.7160390615463257, -3.4900259971618652, -6.13678503036499, -6.34589147567749, -6.87408971786499, -5.48944616317749, -5.77399206161499, -3.3685660362243652, -1.7160390615463257, -3.3685660362243652, -1.7160390615463257, -1.7160390615463257, -5.614987850189209, -1.7160390615463257, -4.639684200286865, -4.12457799911499, -2.9144339561462402, -1.7160390615463257, -6.21594762802124, -5.495259761810303, -3.4900259971618652, -5.386525630950928, -9.392521858215332, -4.677785396575928, -4.677785396575928, -1.7160390615463257, -6.34589147567749, -1.7160390615463257, -3.8766226768493652, -6.13678503036499, -4.639684200286865, -8.246663093566895, -3.4900259971618652, -5.508031368255615, -5.065267086029053, -1.7160390615463257, -0.9920858144760132, -4.12457799911499, -0.9920858144760132, -8.3554048538208, -1.7160390615463257, -4.639684200286865, -3.8766226768493652, -0.9920858144760132, -4.639684200286865, -4.677785396575928, -0.9920858144760132, -4.677785396575928, -3.4900259971618652, -1.7160390615463257, -4.677785396575928, -3.4900259971618652, -9.406285285949707, -6.34589147567749, -1.7160390615463257, -3.4900259971618652, -6.21594762802124, -6.21594762802124, -12.090619087219238, -1.7160390615463257, -0.9920858144760132, -7.34662389755249, -1.7160390615463257, -6.21594762802124, -6.21594762802124, -1.7160390615463257, -3.4900259971618652, -5.495259761810303, -5.77399206161499, -4.12457799911499, -9.017033576965332, -6.34589147567749, -4.677785396575928, -5.614987850189209, -4.639684200286865, -4.12457799911499, -1.7160390615463257, -4.677785396575928, -1.7160390615463257, -3.4900259971618652, -7.949399471282959, -6.34589147567749, -6.264554500579834, -11.322522163391113, -5.065267086029053, -4.12457799911499, -5.614987850189209, -3.8766226768493652, -6.21771764755249]], "generator_names": ["gelu_two_layers/", "gelu_twelve_layers/", "gelu_twenty_four_layers/"]}