{"id": 20284, "input_str": " Packer Ty Montgomery and his mother, Lisa Montgomery, will join foster parents at a rock-climbing wall set up beneath a billboard at 12th St.", "correct_token_str": " and", "generated_token_strs": [" and", " Sal", " and", " in", " in", " and", " and", " former", " and", " in", " in", " in", " in", "\n", " in", " in", " and", "\n", " and", " in", " bookstore", " and", " in", " and", " Kathy", "\n", " and", " NW", " and", " Grey", "\n", " to", " Ed", "\n", " and", " and", " NW", " and", " A", " NW", " that", " in", " In", " in", " in", " in", " in", " NW", " W", " on", " in", " in", " in", " Lower", " and", " and", " and", " looking", " near", " near", " in", " in", "\n", " and", " and", " and", " in", " NW", " and", "\n", " and", " and", " in", " and", " in", " in", " in", " in", " in", " and", "\n", " in", " in", " between", " in", " in", "\n", " and", " and", "\n", " between", " and", " near", " &", " in", " in", " in", " between", " S", " next", " E", " near", " and", "\n", " Pleasant", " and", " The", " in", " in", "\n", " and", " in", " in", " in", " Connect", " in", " in", " and", " and", " in", " near", " Company", "\n", " facing", " and", " NW", " between", " in", " and", " and", " in", " and", " NW", " West", " in", " in", "\n", "\n", " in", "<|endoftext|>", " in", " in", " S", "\n", " W", " nearby", " in", " Athens", " on", " and", " and", " in", " and", " and", " in", " in", " on", " W", " NW", " in", "\n", " in", " South", " in", " in", " with", "\n", " in", " NW", " east", " in", " Read", " and", " Environment", " to", " in", "\n", " and", " owned", " in", " in", " and", " in", "\n", " on", " and", " and", " in", " Ed", " NW", " and", " W", " on", " and", " on", " and", " and", " NW", " for", " NW", "\n", " SE", " in", " in", " street", " It", " and", " And", " NW", " S", " and", " NW", "ap", " in", " and", " in", " between", " and", " and", " in", " and", " NW", " on", " north", " and", " in", " No", " And", " in", " NW", " and", "\n", " NW", " and", "\n", " outside", " Friday", " in", " the", " for", " in", " on", " NE", " with", " in", " (", " and", " at", " near", " for", " in", " in", " including", " NW", " NE", " NW", " and", " eastern", " and", " NW", " between", "\n", " that", " in", " and", " E", " and", " in", " in", " W", " for", " in", " in", "\n", " and", " on", " in", " and", " in", " in", " Rev", " and", " in", " near", " and", " and", " this", " and", " in", " and", " in", " in", "\n", " The", " in", " in", " and", " in", " between", "\n", " in", " in", " NW", " Among", " in", " in", " NE", " Sacrament", " and", " and", " and", " in", " in", " Among", " hands", "\n", " in", " in", " W", " next", "<|endoftext|>", " between", " and", " in", " W", " in", " across", "\n", " in", " and", " in", " and", " in", " NW", " In", " and", " in", " and", " in", "\n", " in", " and", " in", " NW", " and", " between", " between", " in", " for", " and", " \"", " outside", " business", " and", "\n", " NW", " West", " in", " on", " and", " between", " between", " Cait", " and", " in", " NW", "\n", " where", " blank", " in", " between", " Ald", " in", " W", " NW", " in", " in", " NE", " and", " in", " and", " and", " in", " A", " NW", " following", " regarding", " between", " where", " A", " in", " in", " and", " NW", " on", " E", " and", " NW", " The", " in"], "generator_index": 1, "correct_logprobs": [-5.051142692565918, -1.5144641399383545, -0.11274503171443939], "generated_logprobss": [[-5.051142692565918, -11.232799530029297, -5.051142692565918, -6.190587997436523, -6.190587997436523, -5.051142692565918, -5.051142692565918, -14.313447952270508, -5.051142692565918, -6.190587997436523, -6.190587997436523, -6.190587997436523, -6.190587997436523, -4.177469253540039, -6.190587997436523, -6.190587997436523, -5.051142692565918, -4.177469253540039, -5.051142692565918, -6.190587997436523, -10.385868072509766, -5.051142692565918, -6.190587997436523, -5.051142692565918, -9.083647727966309, -4.177469253540039, -5.051142692565918, -7.09682559967041, -5.051142692565918, -15.759727478027344, -4.177469253540039, -6.835809707641602, -7.7583513259887695, -4.177469253540039, -5.051142692565918, -5.051142692565918, -7.09682559967041, -5.051142692565918, -5.925764083862305, -7.09682559967041, -8.860742568969727, -6.190587997436523, -7.783808708190918, -6.190587997436523, -6.190587997436523, -6.190587997436523, -6.190587997436523, -7.09682559967041, -6.2372846603393555, -5.09843635559082, -6.190587997436523, -6.190587997436523, -6.190587997436523, -11.46392822265625, -5.051142692565918, -5.051142692565918, -5.051142692565918, -10.02673053741455, -8.647497177124023, -8.647497177124023, -6.190587997436523, -6.190587997436523, -4.177469253540039, -5.051142692565918, -5.051142692565918, -5.051142692565918, -6.190587997436523, -7.09682559967041, -5.051142692565918, -4.177469253540039, -5.051142692565918, -5.051142692565918, -6.190587997436523, -5.051142692565918, -6.190587997436523, -6.190587997436523, -6.190587997436523, -6.190587997436523, -6.190587997436523, -5.051142692565918, -4.177469253540039, -6.190587997436523, -6.190587997436523, -8.944497108459473, -6.190587997436523, -6.190587997436523, -4.177469253540039, -5.051142692565918, -5.051142692565918, -4.177469253540039, -8.944497108459473, -5.051142692565918, -8.647497177124023, -6.840611457824707, -6.190587997436523, -6.190587997436523, -6.190587997436523, -8.944497108459473, -7.165647506713867, -14.76254940032959, -6.923608779907227, -8.647497177124023, -5.051142692565918, -4.177469253540039, -8.417037010192871, -5.051142692565918, -4.048006057739258, -6.190587997436523, -6.190587997436523, -4.177469253540039, -5.051142692565918, -6.190587997436523, -6.190587997436523, -6.190587997436523, -13.307101249694824, -6.190587997436523, -6.190587997436523, -5.051142692565918, -5.051142692565918, -6.190587997436523, -8.647497177124023, -17.39407730102539, -4.177469253540039, -12.438514709472656, -5.051142692565918, -7.09682559967041, -8.944497108459473, -6.190587997436523, -5.051142692565918, -5.051142692565918, -6.190587997436523, -5.051142692565918, -7.09682559967041, -9.654409408569336, -6.190587997436523, -6.190587997436523, -4.177469253540039, -4.177469253540039, -6.190587997436523, -23.26749610900879, -6.190587997436523, -6.190587997436523, -7.165647506713867, -4.177469253540039, -6.2372846603393555, -10.987039566040039, -6.190587997436523, -11.221938133239746, -5.09843635559082, -5.051142692565918, -5.051142692565918, -6.190587997436523, -5.051142692565918, -5.051142692565918, -6.190587997436523, -6.190587997436523, -5.09843635559082, -6.2372846603393555, -7.09682559967041, -6.190587997436523, -4.177469253540039, -6.190587997436523, -11.778897285461426, -6.190587997436523, -6.190587997436523, -7.617572784423828, -4.177469253540039, -6.190587997436523, -7.09682559967041, -10.905978202819824, -6.190587997436523, -8.970658302307129, -5.051142692565918, -15.382684707641602, -6.835809707641602, -6.190587997436523, -4.177469253540039, -5.051142692565918, -17.362003326416016, -6.190587997436523, -6.190587997436523, -5.051142692565918, -6.190587997436523, -4.177469253540039, -5.09843635559082, -5.051142692565918, -5.051142692565918, -6.190587997436523, -7.7583513259887695, -7.09682559967041, -5.051142692565918, -6.2372846603393555, -5.09843635559082, -5.051142692565918, -5.09843635559082, -5.051142692565918, -5.051142692565918, -7.09682559967041, -7.230210304260254, -7.09682559967041, -4.177469253540039, -9.428998947143555, -6.190587997436523, -6.190587997436523, -9.5288724899292, -9.595471382141113, -5.051142692565918, -9.134328842163086, -7.09682559967041, -7.165647506713867, -5.051142692565918, -7.09682559967041, -12.604532241821289, -6.190587997436523, -5.051142692565918, -6.190587997436523, -8.944497108459473, -5.051142692565918, -5.051142692565918, -6.190587997436523, -5.051142692565918, -7.09682559967041, -5.09843635559082, -11.177227020263672, -5.051142692565918, -6.190587997436523, -9.186508178710938, -9.134328842163086, -6.190587997436523, -7.09682559967041, -5.051142692565918, -4.177469253540039, -7.09682559967041, -5.051142692565918, -4.177469253540039, -12.455476760864258, -9.368979454040527, -6.190587997436523, -7.701295852661133, -7.230210304260254, -6.190587997436523, -5.09843635559082, -9.127604484558105, -7.617572784423828, -6.190587997436523, -7.6388444900512695, -5.051142692565918, -9.096832275390625, -8.647497177124023, -7.230210304260254, -6.190587997436523, -6.190587997436523, -13.181090354919434, -7.09682559967041, -9.127604484558105, -7.09682559967041, -5.051142692565918, -9.622746467590332, -5.051142692565918, -7.09682559967041, -8.944497108459473, -4.177469253540039, -8.860742568969727, -6.190587997436523, -5.051142692565918, -6.923608779907227, -5.051142692565918, -6.190587997436523, -6.190587997436523, -6.2372846603393555, -7.230210304260254, -6.190587997436523, -6.190587997436523, -4.177469253540039, -5.051142692565918, -5.09843635559082, -6.190587997436523, -5.051142692565918, -6.190587997436523, -6.190587997436523, -13.379040718078613, -5.051142692565918, -6.190587997436523, -8.647497177124023, -5.051142692565918, -5.051142692565918, -8.467809677124023, -5.051142692565918, -6.190587997436523, -5.051142692565918, -6.190587997436523, -6.190587997436523, -4.177469253540039, -4.048006057739258, -6.190587997436523, -6.190587997436523, -5.051142692565918, -6.190587997436523, -8.944497108459473, -4.177469253540039, -6.190587997436523, -6.190587997436523, -7.09682559967041, -10.79164981842041, -6.190587997436523, -6.190587997436523, -9.127604484558105, -20.107881546020508, -5.051142692565918, -5.051142692565918, -5.051142692565918, -6.190587997436523, -6.190587997436523, -10.79164981842041, -14.543364524841309, -4.177469253540039, -6.190587997436523, -6.190587997436523, -6.2372846603393555, -14.76254940032959, -23.26749610900879, -8.944497108459473, -5.051142692565918, -6.190587997436523, -6.2372846603393555, -6.190587997436523, -11.291007041931152, -4.177469253540039, -6.190587997436523, -5.051142692565918, -6.190587997436523, -5.051142692565918, -6.190587997436523, -7.09682559967041, -7.783808708190918, -5.051142692565918, -6.190587997436523, -5.051142692565918, -6.190587997436523, -4.177469253540039, -6.190587997436523, -5.051142692565918, -6.190587997436523, -7.09682559967041, -5.051142692565918, -8.944497108459473, -8.944497108459473, -6.190587997436523, -7.230210304260254, -5.051142692565918, -8.480486869812012, -12.455476760864258, -12.856839179992676, -5.051142692565918, -4.177469253540039, -7.09682559967041, -9.654409408569336, -6.190587997436523, -5.09843635559082, -5.051142692565918, -8.944497108459473, -8.944497108459473, -18.51178550720215, -5.051142692565918, -6.190587997436523, -7.09682559967041, -4.177469253540039, -9.73437786102295, -16.767637252807617, -6.190587997436523, -8.944497108459473, -12.680257797241211, -6.190587997436523, -6.2372846603393555, -7.09682559967041, -6.190587997436523, -6.190587997436523, -9.127604484558105, -5.051142692565918, -6.190587997436523, -5.051142692565918, -5.051142692565918, -6.190587997436523, -5.925764083862305, -7.09682559967041, -9.537999153137207, -10.594816207885742, -8.944497108459473, -9.73437786102295, -5.925764083862305, -6.190587997436523, -6.190587997436523, -5.051142692565918, -7.09682559967041, -5.09843635559082, -6.923608779907227, -5.051142692565918, -7.09682559967041, -4.048006057739258, -6.190587997436523], [-1.5144641399383545, -11.837477684020996, -1.5144641399383545, -1.2715442180633545, -1.2715442180633545, -1.5144641399383545, -1.5144641399383545, -9.611449241638184, -1.5144641399383545, -1.2715442180633545, -1.2715442180633545, -1.2715442180633545, -1.2715442180633545, -2.5855624675750732, -1.2715442180633545, -1.2715442180633545, -1.5144641399383545, -2.5855624675750732, -1.5144641399383545, -1.2715442180633545, -12.504607200622559, -1.5144641399383545, -1.2715442180633545, -1.5144641399383545, -12.241324424743652, -2.5855624675750732, -1.5144641399383545, -2.476362943649292, -1.5144641399383545, -11.473296165466309, -2.5855624675750732, -4.834982872009277, -9.738615989685059, -2.5855624675750732, -1.5144641399383545, -1.5144641399383545, -2.476362943649292, -1.5144641399383545, -5.551558494567871, -2.476362943649292, -5.20987606048584, -1.2715442180633545, -5.461791038513184, -1.2715442180633545, -1.2715442180633545, -1.2715442180633545, -1.2715442180633545, -2.476362943649292, -4.092551231384277, -3.378035306930542, -1.2715442180633545, -1.2715442180633545, -1.2715442180633545, -9.986617088317871, -1.5144641399383545, -1.5144641399383545, -1.5144641399383545, -9.177596092224121, -4.272704124450684, -4.272704124450684, -1.2715442180633545, -1.2715442180633545, -2.5855624675750732, -1.5144641399383545, -1.5144641399383545, -1.5144641399383545, -1.2715442180633545, -2.476362943649292, -1.5144641399383545, -2.5855624675750732, -1.5144641399383545, -1.5144641399383545, -1.2715442180633545, -1.5144641399383545, -1.2715442180633545, -1.2715442180633545, -1.2715442180633545, -1.2715442180633545, -1.2715442180633545, -1.5144641399383545, -2.5855624675750732, -1.2715442180633545, -1.2715442180633545, -3.9457767009735107, -1.2715442180633545, -1.2715442180633545, -2.5855624675750732, -1.5144641399383545, -1.5144641399383545, -2.5855624675750732, -3.9457767009735107, -1.5144641399383545, -4.272704124450684, -5.422591209411621, -1.2715442180633545, -1.2715442180633545, -1.2715442180633545, -3.9457767009735107, -5.073081016540527, -4.891295433044434, -4.865355491638184, -4.272704124450684, -1.5144641399383545, -2.5855624675750732, -10.265776634216309, -1.5144641399383545, -4.487914085388184, -1.2715442180633545, -1.2715442180633545, -2.5855624675750732, -1.5144641399383545, -1.2715442180633545, -1.2715442180633545, -1.2715442180633545, -10.780440330505371, -1.2715442180633545, -1.2715442180633545, -1.5144641399383545, -1.5144641399383545, -1.2715442180633545, -4.272704124450684, -11.076323509216309, -2.5855624675750732, -8.198019981384277, -1.5144641399383545, -2.476362943649292, -3.9457767009735107, -1.2715442180633545, -1.5144641399383545, -1.5144641399383545, -1.2715442180633545, -1.5144641399383545, -2.476362943649292, -5.163153648376465, -1.2715442180633545, -1.2715442180633545, -2.5855624675750732, -2.5855624675750732, -1.2715442180633545, -5.977416038513184, -1.2715442180633545, -1.2715442180633545, -5.073081016540527, -2.5855624675750732, -4.092551231384277, -9.827940940856934, -1.2715442180633545, -11.181014060974121, -3.378035306930542, -1.5144641399383545, -1.5144641399383545, -1.2715442180633545, -1.5144641399383545, -1.5144641399383545, -1.2715442180633545, -1.2715442180633545, -3.378035306930542, -4.092551231384277, -2.476362943649292, -1.2715442180633545, -2.5855624675750732, -1.2715442180633545, -5.839629173278809, -1.2715442180633545, -1.2715442180633545, -6.300276756286621, -2.5855624675750732, -1.2715442180633545, -2.476362943649292, -7.084029197692871, -1.2715442180633545, -9.592589378356934, -1.5144641399383545, -14.32102108001709, -4.834982872009277, -1.2715442180633545, -2.5855624675750732, -1.5144641399383545, -10.860709190368652, -1.2715442180633545, -1.2715442180633545, -1.5144641399383545, -1.2715442180633545, -2.5855624675750732, -3.378035306930542, -1.5144641399383545, -1.5144641399383545, -1.2715442180633545, -9.738615989685059, -2.476362943649292, -1.5144641399383545, -4.092551231384277, -3.378035306930542, -1.5144641399383545, -3.378035306930542, -1.5144641399383545, -1.5144641399383545, -2.476362943649292, -4.998686790466309, -2.476362943649292, -2.5855624675750732, -5.576910972595215, -1.2715442180633545, -1.2715442180633545, -10.108229637145996, -7.402350425720215, -1.5144641399383545, -6.30771541595459, -2.476362943649292, -5.073081016540527, -1.5144641399383545, -2.476362943649292, -11.917616844177246, -1.2715442180633545, -1.5144641399383545, -1.2715442180633545, -3.9457767009735107, -1.5144641399383545, -1.5144641399383545, -1.2715442180633545, -1.5144641399383545, -2.476362943649292, -3.378035306930542, -7.282256126403809, -1.5144641399383545, -1.2715442180633545, -7.458662986755371, -6.30771541595459, -1.2715442180633545, -2.476362943649292, -1.5144641399383545, -2.5855624675750732, -2.476362943649292, -1.5144641399383545, -2.5855624675750732, -6.728423118591309, -7.101943016052246, -1.2715442180633545, -6.990767478942871, -4.998686790466309, -1.2715442180633545, -3.378035306930542, -5.038939476013184, -6.300276756286621, -1.2715442180633545, -5.632956504821777, -1.5144641399383545, -5.053038597106934, -4.272704124450684, -4.998686790466309, -1.2715442180633545, -1.2715442180633545, -7.650130271911621, -2.476362943649292, -5.038939476013184, -2.476362943649292, -1.5144641399383545, -9.896491050720215, -1.5144641399383545, -2.476362943649292, -3.9457767009735107, -2.5855624675750732, -5.20987606048584, -1.2715442180633545, -1.5144641399383545, -4.865355491638184, -1.5144641399383545, -1.2715442180633545, -1.2715442180633545, -4.092551231384277, -4.998686790466309, -1.2715442180633545, -1.2715442180633545, -2.5855624675750732, -1.5144641399383545, -3.378035306930542, -1.2715442180633545, -1.5144641399383545, -1.2715442180633545, -1.2715442180633545, -11.407111167907715, -1.5144641399383545, -1.2715442180633545, -4.272704124450684, -1.5144641399383545, -1.5144641399383545, -6.557280540466309, -1.5144641399383545, -1.2715442180633545, -1.5144641399383545, -1.2715442180633545, -1.2715442180633545, -2.5855624675750732, -4.487914085388184, -1.2715442180633545, -1.2715442180633545, -1.5144641399383545, -1.2715442180633545, -3.9457767009735107, -2.5855624675750732, -1.2715442180633545, -1.2715442180633545, -2.476362943649292, -8.768340110778809, -1.2715442180633545, -1.2715442180633545, -5.038939476013184, -13.786986351013184, -1.5144641399383545, -1.5144641399383545, -1.5144641399383545, -1.2715442180633545, -1.2715442180633545, -8.768340110778809, -13.323088645935059, -2.5855624675750732, -1.2715442180633545, -1.2715442180633545, -4.092551231384277, -4.891295433044434, -5.977416038513184, -3.9457767009735107, -1.5144641399383545, -1.2715442180633545, -4.092551231384277, -1.2715442180633545, -6.964720726013184, -2.5855624675750732, -1.2715442180633545, -1.5144641399383545, -1.2715442180633545, -1.5144641399383545, -1.2715442180633545, -2.476362943649292, -5.461791038513184, -1.5144641399383545, -1.2715442180633545, -1.5144641399383545, -1.2715442180633545, -2.5855624675750732, -1.2715442180633545, -1.5144641399383545, -1.2715442180633545, -2.476362943649292, -1.5144641399383545, -3.9457767009735107, -3.9457767009735107, -1.2715442180633545, -4.998686790466309, -1.5144641399383545, -6.291777610778809, -6.728423118591309, -11.904044151306152, -1.5144641399383545, -2.5855624675750732, -2.476362943649292, -5.163153648376465, -1.2715442180633545, -3.378035306930542, -1.5144641399383545, -3.9457767009735107, -3.9457767009735107, -14.266585350036621, -1.5144641399383545, -1.2715442180633545, -2.476362943649292, -2.5855624675750732, -5.648543357849121, -14.864371299743652, -1.2715442180633545, -3.9457767009735107, -9.859282493591309, -1.2715442180633545, -4.092551231384277, -2.476362943649292, -1.2715442180633545, -1.2715442180633545, -5.038939476013184, -1.5144641399383545, -1.2715442180633545, -1.5144641399383545, -1.5144641399383545, -1.2715442180633545, -5.551558494567871, -2.476362943649292, -7.221495628356934, -9.45377254486084, -3.9457767009735107, -5.648543357849121, -5.551558494567871, -1.2715442180633545, -1.2715442180633545, -1.5144641399383545, -2.476362943649292, -3.378035306930542, -4.865355491638184, -1.5144641399383545, -2.476362943649292, -4.487914085388184, -1.2715442180633545], [-0.11274503171443939, -12.501764297485352, -0.11274503171443939, -5.0534186363220215, -5.0534186363220215, -0.11274503171443939, -0.11274503171443939, -13.45814323425293, -0.11274503171443939, -5.0534186363220215, -5.0534186363220215, -5.0534186363220215, -5.0534186363220215, -5.419625759124756, -5.0534186363220215, -5.0534186363220215, -0.11274503171443939, -5.419625759124756, -0.11274503171443939, -5.0534186363220215, -17.57123374938965, -0.11274503171443939, -5.0534186363220215, -0.11274503171443939, -15.18726921081543, -5.419625759124756, -0.11274503171443939, -4.455026149749756, -0.11274503171443939, -16.87752342224121, -5.419625759124756, -6.730641841888428, -11.227762222290039, -5.419625759124756, -0.11274503171443939, -0.11274503171443939, -4.455026149749756, -0.11274503171443939, -9.664121627807617, -4.455026149749756, -8.676656723022461, -5.0534186363220215, -10.399263381958008, -5.0534186363220215, -5.0534186363220215, -5.0534186363220215, -5.0534186363220215, -4.455026149749756, -6.0839362144470215, -6.20148229598999, -5.0534186363220215, -5.0534186363220215, -5.0534186363220215, -12.587263107299805, -0.11274503171443939, -0.11274503171443939, -0.11274503171443939, -12.140314102172852, -6.143208980560303, -6.143208980560303, -5.0534186363220215, -5.0534186363220215, -5.419625759124756, -0.11274503171443939, -0.11274503171443939, -0.11274503171443939, -5.0534186363220215, -4.455026149749756, -0.11274503171443939, -5.419625759124756, -0.11274503171443939, -0.11274503171443939, -5.0534186363220215, -0.11274503171443939, -5.0534186363220215, -5.0534186363220215, -5.0534186363220215, -5.0534186363220215, -5.0534186363220215, -0.11274503171443939, -5.419625759124756, -5.0534186363220215, -5.0534186363220215, -4.6538214683532715, -5.0534186363220215, -5.0534186363220215, -5.419625759124756, -0.11274503171443939, -0.11274503171443939, -5.419625759124756, -4.6538214683532715, -0.11274503171443939, -6.143208980560303, -4.6887335777282715, -5.0534186363220215, -5.0534186363220215, -5.0534186363220215, -4.6538214683532715, -5.589475154876709, -10.144685745239258, -6.252980709075928, -6.143208980560303, -0.11274503171443939, -5.419625759124756, -11.925481796264648, -0.11274503171443939, -8.667428970336914, -5.0534186363220215, -5.0534186363220215, -5.419625759124756, -0.11274503171443939, -5.0534186363220215, -5.0534186363220215, -5.0534186363220215, -12.199220657348633, -5.0534186363220215, -5.0534186363220215, -0.11274503171443939, -0.11274503171443939, -5.0534186363220215, -6.143208980560303, -14.223966598510742, -5.419625759124756, -11.787931442260742, -0.11274503171443939, -4.455026149749756, -4.6538214683532715, -5.0534186363220215, -0.11274503171443939, -0.11274503171443939, -5.0534186363220215, -0.11274503171443939, -4.455026149749756, -8.022119522094727, -5.0534186363220215, -5.0534186363220215, -5.419625759124756, -5.419625759124756, -5.0534186363220215, -8.134572982788086, -5.0534186363220215, -5.0534186363220215, -5.589475154876709, -5.419625759124756, -6.0839362144470215, -12.34758186340332, -5.0534186363220215, -16.09364128112793, -6.20148229598999, -0.11274503171443939, -0.11274503171443939, -5.0534186363220215, -0.11274503171443939, -0.11274503171443939, -5.0534186363220215, -5.0534186363220215, -6.20148229598999, -6.0839362144470215, -4.455026149749756, -5.0534186363220215, -5.419625759124756, -5.0534186363220215, -7.192845821380615, -5.0534186363220215, -5.0534186363220215, -8.226846694946289, -5.419625759124756, -5.0534186363220215, -4.455026149749756, -10.717123031616211, -5.0534186363220215, -11.506597518920898, -0.11274503171443939, -16.846899032592773, -6.730641841888428, -5.0534186363220215, -5.419625759124756, -0.11274503171443939, -14.69264030456543, -5.0534186363220215, -5.0534186363220215, -0.11274503171443939, -5.0534186363220215, -5.419625759124756, -6.20148229598999, -0.11274503171443939, -0.11274503171443939, -5.0534186363220215, -11.227762222290039, -4.455026149749756, -0.11274503171443939, -6.0839362144470215, -6.20148229598999, -0.11274503171443939, -6.20148229598999, -0.11274503171443939, -0.11274503171443939, -4.455026149749756, -7.862374782562256, -4.455026149749756, -5.419625759124756, -4.7907233238220215, -5.0534186363220215, -5.0534186363220215, -12.855741500854492, -11.217153549194336, -0.11274503171443939, -7.192674160003662, -4.455026149749756, -5.589475154876709, -0.11274503171443939, -4.455026149749756, -17.007421493530273, -5.0534186363220215, -0.11274503171443939, -5.0534186363220215, -4.6538214683532715, -0.11274503171443939, -0.11274503171443939, -5.0534186363220215, -0.11274503171443939, -4.455026149749756, -6.20148229598999, -9.633493423461914, -0.11274503171443939, -5.0534186363220215, -10.505338668823242, -7.192674160003662, -5.0534186363220215, -4.455026149749756, -0.11274503171443939, -5.419625759124756, -4.455026149749756, -0.11274503171443939, -5.419625759124756, -8.941701889038086, -11.073598861694336, -5.0534186363220215, -9.09827995300293, -7.862374782562256, -5.0534186363220215, -6.20148229598999, -5.439267635345459, -8.226846694946289, -5.0534186363220215, -7.735402584075928, -0.11274503171443939, -7.090840816497803, -6.143208980560303, -7.862374782562256, -5.0534186363220215, -5.0534186363220215, -11.026063919067383, -4.455026149749756, -5.439267635345459, -4.455026149749756, -0.11274503171443939, -13.588605880737305, -0.11274503171443939, -4.455026149749756, -4.6538214683532715, -5.419625759124756, -8.676656723022461, -5.0534186363220215, -0.11274503171443939, -6.252980709075928, -0.11274503171443939, -5.0534186363220215, -5.0534186363220215, -6.0839362144470215, -7.862374782562256, -5.0534186363220215, -5.0534186363220215, -5.419625759124756, -0.11274503171443939, -6.20148229598999, -5.0534186363220215, -0.11274503171443939, -5.0534186363220215, -5.0534186363220215, -16.12343406677246, -0.11274503171443939, -5.0534186363220215, -6.143208980560303, -0.11274503171443939, -0.11274503171443939, -10.291913986206055, -0.11274503171443939, -5.0534186363220215, -0.11274503171443939, -5.0534186363220215, -5.0534186363220215, -5.419625759124756, -8.667428970336914, -5.0534186363220215, -5.0534186363220215, -0.11274503171443939, -5.0534186363220215, -4.6538214683532715, -5.419625759124756, -5.0534186363220215, -5.0534186363220215, -4.455026149749756, -12.74928092956543, -5.0534186363220215, -5.0534186363220215, -5.439267635345459, -14.720800399780273, -0.11274503171443939, -0.11274503171443939, -0.11274503171443939, -5.0534186363220215, -5.0534186363220215, -12.74928092956543, -15.994916915893555, -5.419625759124756, -5.0534186363220215, -5.0534186363220215, -6.0839362144470215, -10.144685745239258, -8.134572982788086, -4.6538214683532715, -0.11274503171443939, -5.0534186363220215, -6.0839362144470215, -5.0534186363220215, -8.295869827270508, -5.419625759124756, -5.0534186363220215, -0.11274503171443939, -5.0534186363220215, -0.11274503171443939, -5.0534186363220215, -4.455026149749756, -10.399263381958008, -0.11274503171443939, -5.0534186363220215, -0.11274503171443939, -5.0534186363220215, -5.419625759124756, -5.0534186363220215, -0.11274503171443939, -5.0534186363220215, -4.455026149749756, -0.11274503171443939, -4.6538214683532715, -4.6538214683532715, -5.0534186363220215, -7.862374782562256, -0.11274503171443939, -9.788091659545898, -8.941701889038086, -12.146806716918945, -0.11274503171443939, -5.419625759124756, -4.455026149749756, -8.022119522094727, -5.0534186363220215, -6.20148229598999, -0.11274503171443939, -4.6538214683532715, -4.6538214683532715, -15.67662239074707, -0.11274503171443939, -5.0534186363220215, -4.455026149749756, -5.419625759124756, -8.002729415893555, -16.80943489074707, -5.0534186363220215, -4.6538214683532715, -11.307653427124023, -5.0534186363220215, -6.0839362144470215, -4.455026149749756, -5.0534186363220215, -5.0534186363220215, -5.439267635345459, -0.11274503171443939, -5.0534186363220215, -0.11274503171443939, -0.11274503171443939, -5.0534186363220215, -9.664121627807617, -4.455026149749756, -9.670309066772461, -11.43592643737793, -4.6538214683532715, -8.002729415893555, -9.664121627807617, -5.0534186363220215, -5.0534186363220215, -0.11274503171443939, -4.455026149749756, -6.20148229598999, -6.252980709075928, -0.11274503171443939, -4.455026149749756, -8.667428970336914, -5.0534186363220215]], "generator_names": ["gelu_two_layers/", "gelu_twelve_layers/", "gelu_twenty_four_layers/"]}