["There", " is", " lots", " of", " interesting", " information", " in", " the", " latest", " National", " Household", " Survey", " data", " tr", "anche", ",", " on", " income", " and", " housing", ",", " which", " Statistics", " Canada", " published", " this", " morning", ".", " Did", " you", " know", " Canadians", " in", " the", " top", " one", " per", " cent", " of", " the", " income", " distribution", " are", " mostly", " educated", " older", " white", " men", "?", " Or", " that", " fully", " a", " quarter", " of", " Canadians", " spend", " 30", " per", " cent", " or", " more", " of", " their", " total", " \u2014", " not", " disposable", " \u2014", " income", " on", " things", " like", " rent", " and", " mortgage", "?", " OK", ",", " fine", ",", " if", " you", " every", " read", " the", " news", " you", " probably", " suspected", " as", " much", ".", " Still", ",", " now", " you", " can", " quote", " the", " exact", " numbers", " at", " cocktail", " parties", " with", " the", " confidence", " that", " comes", " from", " Stats", "Can", "\ufffd", "\ufffd", "s", " quality", " guarantee", ".", "\n", "\n", "If", " you", " care", " about", " accuracy", ",", " though", ",", " you", " might", " wish", " to", " avoid", " drawing", " conclusions", " about", " what", " today", "\ufffd", "\ufffd", "s", " NHS", " numbers", " tells", " us", " about", " income", " and", " housing", " trends", ".", " How", " much", " has", " income", " inequality", " widened", " \u2014", " or", " shrunk", "?", " Are", " the", " poor", " struggling", " more", " or", " less", "?", " And", " what", " percentage", " of", " Canadians", " used", " to", " spend", " a", " third", " or", " more", " of", " their", " income", " on", " shelter", " five", " years", " ago", "?", " If", " you", " don", "\ufffd", "\ufffd", "t", " have", " a", " Ph", ".", "D", ".", " in", " statistics", " or", " economics", ",", " Stats", "Can", "\ufffd", "\ufffd", "s", " friendly", " advice", " is", ":", " Don", "\ufffd", "\ufffd", "t", " try", " to", " answer", " those", " questions", " on", " your", " own", ".", " Simple", " math", " is", " enough", " if", " you", " want", " to", " use", " NHS", " data", " to", ",", " say", ",", " see", " the", " distribution", " of", " low", "-", "income", " people", " across", " provinces", " or", " ethnic", " and", " age", " groups", ".", " But", " extrap", "ol", "ating", " trends", " across", " the", " years", " now", " requires", " field", "-", "specific", " expertise", ".", " And", " even", " the", " pros", " must", " tread", " carefully", ",", " judging", " from", " Stats", "Can", "\ufffd", "\ufffd", "s", " lengthy", " guide", " to", " the", " pitfalls", " of", " comparing", " the", " NHS", ",", " a", " voluntary", " survey", ",", " to", " the", " old", ",", " mandatory", " long", "-", "form", " census", ".", "\n", "\n", "As", " my", " E", "con", "ow", "atch", " colleague", " Kevin", " Mill", "igan", " explained", " some", " time", " ago", ",", " the", " problem", " with", " terminating", " the", " long", "-", "form", " census", " is", " that", " you", " never", " know", " why", " people", " might", " decide", " not", " to", " respond", " to", " a", " voluntary", " questionnaire", ".", " If", " they", " do", " so", " at", " random", ",", " you", "\ufffd", "\ufffd", "re", " fine", ":", " The", " new", ",", " voluntary", " data", " sample", " is", " comparable", " with", " the", " old", ",", " mandatory", ",", " randomized", " samples", ".", " But", " if", ",", " for", " example", ",", " poorer", " people", " are", " more", " likely", " not", " to", " answer", ",", " then", " you", " have", " a", " problem", ".", " At", " least", " a", " couple", " of", " Canadian", " studies", " based", " on", " both", " voluntary", " and", " mandatory", " income", " surveys", " have", " found", " precisely", " this", " issue", " with", " low", "-", "income", " respondents", ".", "\n", "\n", "When", " I", " asked", " Alison", " Hale", ",", " director", " of", " income", " statistics", " at", " Stats", "Can", ",", " about", " compar", "ability", " problems", " between", " NHS", " and", " the", " census", ",", " she", " pointed", " me", " to", " the", " table", " below", " (", "click", " here", " to", " see", " a", " larger", " image", "):", "\n", "\n", "The", " key", " columns", " are", " the", " one", " on", " the", " right", ",", " which", " show", " the", " percentage", " change", " between", " 2005", " and", " 2010", " data", " for", " various", " income", " measures", " as", " captured", " by", " three", " different", " sources", ":", " The", " NHS", "/", "c", "ensus", ",", " the", " Survey", " of", " Labour", " and", " Income", " Dynamics", " and", " the", " T", "1", " Family", " File", ".", " As", " you", " can", " see", ",", " trends", " derived", " from", " the", " an", " NHS", "-", "c", "ensus", " comparison", " generally", " do", " not", " line", " up", " with", " either", " of", " continuous", " series", ".", "\n", "\n", "This", " holds", " true", " for", " housing", " trends", " as", " well", ",", " said", " Hale", ",", " with", " one", " exception", ":", " The", " home", "-", "owners", "hip", " rate", ".", " There", ",", " the", " NHS", "/", "C", "ensus", " tells", " exactly", " the", " same", " story", " as", " other", " surveys", " of", " home", "-", "owners", "hip", ":", " The", " share", " of", " Canadians", " who", " own", " their", " home", " has", " climbed", " to", " 69", " per", " cent", ",", " up", " from", " 68", ".", "4", " per", " cent", ".", "\n", "\n", "Some", "how", ",", " though", ",", " I", " don", "\ufffd", "\ufffd", "t", " think", " that", "\ufffd", "\ufffd", "s", " the", " kind", " of", " insight", " that", "\ufffd", "\ufffd", "s", " going", " to", " wow", " a", " cocktail", " party", " audience", "."]